signet/__init__.py
signet/command/__init__.py
signet/command/build_signet.py
signet/command/sign_code.py
signet/command/lib/README.txt
signet/command/lib/sha1.cpp
signet/command/lib/sha1.h
signet/command/lib/verifytrust.cpp
signet/command/lib/verifytrust.h
signet/command/static/READ.txt
signet/command/static/app.ico
signet/command/templates/README.txt
signet/command/templates/loader.cpp
signet/command/templates/loader.h
signet-3.0.2.dist-info/METADATA
signet-3.0.2.dist-info/WHEEL
signet-3.0.2.dist-info/top_level.txt
signet-3.0.2.dist-info/RECORD
