Metadata-Version: 2.1
Name: signet
Version: 3.0.2
Summary: Signet provides support for building and delivering tamper resistant python to your users and customers.
Home-page: http://jamercee.github.io/signet
Author: Jim Carroll
Author-email: jim@carroll.com
License: Signet is licensed under the 3-clause BSD License
Download-URL: http://github.com/jamercee/signet
Platform: UNKNOWN
Classifier: Development Status :: 5 - Production/Stable
Classifier: Environment :: Console
Classifier: Intended Audience :: Developers
Classifier: License :: OSI Approved :: BSD License
Classifier: Natural Language :: English
Classifier: Operating System :: OS Independent
Classifier: Topic :: Security
Classifier: Topic :: Software Development :: Build Tools
Classifier: Topic :: System :: Software Distribution
Requires-Dist: pywincert
